roomsage_utils/__init__.py
roomsage_utils/api_login_controller.py
roomsage_utils/country_codes_transformer.py
roomsage_utils/datetime_utils.py
roomsage_utils/dict_utils.py
roomsage_utils/directory_utils.py
roomsage_utils/json_utils.py
roomsage_utils/logging_initializer.py
roomsage_utils/naive_bayes.py
roomsage_utils/performance_testing.py
roomsage_utils/roomsage_mailing_service.py
roomsage_utils/run_forever.py
roomsage_utils/test_logging.py
roomsage_utils/test_logging_2.py
roomsage_utils/test_utils.py
roomsage_utils-1.0.dist-info/METADATA
roomsage_utils-1.0.dist-info/WHEEL
roomsage_utils-1.0.dist-info/top_level.txt
roomsage_utils-1.0.dist-info/RECORD
