Metadata-Version: 2.1
Name: roomsage-utils
Version: 1.0
Summary: RoomSage library with util functions
Home-page: UNKNOWN
License: UNKNOWN
Platform: UNKNOWN
Classifier: Programming Language :: Python :: 3.6
Requires-Python: >=3.6
